tcinter-0.0.6.dist-info/RECORD
tcinter-0.0.6.dist-info/WHEEL
tcinter-0.0.6.dist-info/top_level.txt
tcinter-0.0.6.dist-info/METADATA
tcinter-0.0.6.dist-info/licenses/LICENSE
tcinter/constants.py
tcinter/__init__.py
tcinter/_tcinter.so
tcinter/interp.py
tcinter/__main__.py
tcinter/.dylibs/Python
