Metadata-Version: 2.4
Name: tcinter
Version: 0.0.6
Summary: .
Author: Claudio M. Perez
License: A. HISTORY OF THE SOFTWARE
Project-URL: Repository, http://github.com/claudioperez/tcinter
Classifier: Development Status :: 5 - Production/Stable
Classifier: Intended Audience :: Developers
Classifier: Programming Language :: Python :: 3
Classifier: Programming Language :: Python :: 3 :: Only
License-File: LICENSE
Dynamic: license-file
